jsonsubschema/__init__.py
jsonsubschema/_canonicalization.py
jsonsubschema/_checkers.py
jsonsubschema/_constants.py
jsonsubschema/_utils.py
jsonsubschema/api.py
jsonsubschema/cli.py
jsonsubschema/config.py
jsonsubschema/exceptions.py
jsonsubschema_master-0.0.7.dist-info/licenses/LICENSE.txt
jsonsubschema_master-0.0.7.dist-info/METADATA
jsonsubschema_master-0.0.7.dist-info/WHEEL
jsonsubschema_master-0.0.7.dist-info/entry_points.txt
jsonsubschema_master-0.0.7.dist-info/top_level.txt
jsonsubschema_master-0.0.7.dist-info/RECORD
