Metadata-Version: 2.4
Name: jsonsubschema-master
Version: 0.0.7
Summary: An up-to-date fork of jsonsubschema synced with the latest master branch
Home-page: https://github.com/yourusername/jsonsubschema
Author: Andrew Habib, Avraham Shinnar, Martin Hirzel (updated by Your Name)
Author-email: your.email@example.com
License: Apache License 2.0
Classifier: Programming Language :: Python :: 3
Classifier: License :: OSI Approved :: Apache Software License
Classifier: Operating System :: OS Independent
Requires-Python: >=3.6
License-File: LICENSE.txt
Requires-Dist: portion
Requires-Dist: greenery>=4.0.0
Requires-Dist: jsonschema
Requires-Dist: jsonref
Dynamic: author
Dynamic: author-email
Dynamic: classifier
Dynamic: description
Dynamic: description-content-type
Dynamic: home-page
Dynamic: license
Dynamic: license-file
Dynamic: requires-dist
Dynamic: requires-python
Dynamic: summary
